DeepINN/__about__.py
DeepINN/__init__.py
DeepINN/config.py
DeepINN/display.py
DeepINN/model.py
DeepINN/backend/__init__.py
DeepINN/backend/utils.py
DeepINN/constraint/__init__.py
DeepINN/constraint/gradients.py
DeepINN/constraint/losses.py
DeepINN/constraint/templates.py
DeepINN/domain/__init__.py
DeepINN/domain/base.py
DeepINN/domain/standard.py
DeepINN/geometry/__init__.py
DeepINN/geometry/conditions/__init__.py
DeepINN/geometry/conditions/condition.py
DeepINN/geometry/conditions/deeponet_condition.py
DeepINN/geometry/domains/__init__.py
DeepINN/geometry/domains/domain.py
DeepINN/geometry/domains/domain0D/__init__.py
DeepINN/geometry/domains/domain0D/point.py
DeepINN/geometry/domains/domain1D/__init__.py
DeepINN/geometry/domains/domain1D/interval.py
DeepINN/geometry/domains/domain2D/__init__.py
DeepINN/geometry/domains/domain2D/circle.py
DeepINN/geometry/domains/domain2D/parallelogram.py
DeepINN/geometry/domains/domain2D/shapely_polygon.py
DeepINN/geometry/domains/domain2D/triangle.py
DeepINN/geometry/domains/domain3D/__init__.py
DeepINN/geometry/domains/domain3D/sphere.py
DeepINN/geometry/domains/domain3D/trimesh_polyhedron.py
DeepINN/geometry/domains/functionsets/__init__.py
DeepINN/geometry/domains/functionsets/functionset.py
DeepINN/geometry/samplers/__init__.py
DeepINN/geometry/samplers/data_samplers.py
DeepINN/geometry/samplers/grid_samplers.py
DeepINN/geometry/samplers/plot_samplers.py
DeepINN/geometry/samplers/random_samplers.py
DeepINN/geometry/samplers/sampler_base.py
DeepINN/geometry/spaces/__init__.py
DeepINN/geometry/spaces/functionspace.py
DeepINN/geometry/spaces/points.py
DeepINN/geometry/spaces/space.py
DeepINN/nn/FCNN.py
DeepINN/nn/__init__.py
DeepINN/nn/base.py
DeepINN/nn/utils.py
DeepINN/utils/__init__.py
DeepINN/utils/callbacks.py
DeepINN/utils/differentialoperators.py
DeepINN/utils/evaluation.py
DeepINN/utils/user_fun.py
DeepINN/utils/data/__init__.py
DeepINN/utils/data/dataloader.py
DeepINN/utils/data/deeponet_dataloader.py
DeepINN-1.0.0.dist-info/LICENSE
DeepINN-1.0.0.dist-info/METADATA
DeepINN-1.0.0.dist-info/WHEEL
DeepINN-1.0.0.dist-info/top_level.txt
DeepINN-1.0.0.dist-info/RECORD
