Metadata-Version: 2.1
Name: DeepINN
Version: 1.0.0
Summary: A Physics-informed neural network (PINN) library.
Home-page: https://deepinn.readthedocs.io/en/latest/index.html
Author: Prakhar Sharma
Author-email: prakhars962@gmail.com
License: UNKNOWN
Keywords: Differential equations,Physics-informed neural networks
Platform: UNKNOWN
Classifier: Development Status :: 4 - Beta
Classifier: Intended Audience :: Science/Research
Classifier: Programming Language :: Python :: 3
Classifier: Operating System :: Unix
License-File: LICENSE
Requires-Dist: numpy
